hexia_pages/__init__.py
hexia_pages/admin.py
hexia_pages/apps.py
hexia_pages/config.py
hexia_pages/models.py
hexia_pages/tests.py
hexia_pages/urls.py
hexia_pages/views.py
hexia_pages/migrations/0001_initial.py
hexia_pages/migrations/__init__.py
hexia_pages/templates/hexia_pages/page_detail.html
hexia_pages-1.0.1.dist-info/DESCRIPTION.rst
hexia_pages-1.0.1.dist-info/METADATA
hexia_pages-1.0.1.dist-info/RECORD
hexia_pages-1.0.1.dist-info/WHEEL
hexia_pages-1.0.1.dist-info/metadata.json
hexia_pages-1.0.1.dist-info/top_level.txt
migrations/0001_initial.py
migrations/__init__.py
