Metadata-Version: 2.0
Name: hexia-pages
Version: 1.0.1
Summary: A simple Django Page app.
Home-page: https://github.com/HenryMehta/hexia-pages
Author: Henry Mehta
Author-email: hjsmehta@gmail.com
License: MIT License
Keywords: django page app
Platform: UNKNOWN
Classifier: Environment :: Web Environment
Classifier: Framework :: Django
Classifier: Framework :: Django :: 2.0
Classifier: Intended Audience :: Developers
Classifier: License :: OSI Approved :: MIT License
Classifier: Operating System :: OS Independent
Classifier: Programming Language :: Python
Classifier: Programming Language :: Python :: 3.5
Classifier: Topic :: Internet :: WWW/HTTP
Classifier: Topic :: Internet :: WWW/HTTP :: Dynamic Content
Requires-Dist: django-ckeditor
